startai/__init__.py
startai/_version.py
startai/func_wrapper.py
startai/compiler/_compiler.so
startai/compiler/compiler.py
startai/compiler/replace_with.py
startai/compiler/utils/C.so
startai/compiler/utils/CC.so
startai/compiler/utils/CD.so
startai/compiler/utils/CI.so
startai/compiler/utils/CL.so
startai/compiler/utils/CM.so
startai/compiler/utils/CV.so
startai/compiler/utils/CX.so
startai/compiler/utils/D.so
startai/compiler/utils/DC.so
startai/compiler/utils/DD.so
startai/compiler/utils/DI.so
startai/compiler/utils/DL.so
startai/compiler/utils/DM.so
startai/compiler/utils/DV.so
startai/compiler/utils/DX.so
startai/compiler/utils/I.so
startai/compiler/utils/IC.so
startai/compiler/utils/ID.so
startai/compiler/utils/II.so
startai/compiler/utils/IIC.so
startai/compiler/utils/IID.so
startai/compiler/utils/III.so
startai/compiler/utils/IIL.so
startai/compiler/utils/IIM.so
startai/compiler/utils/IIV.so
startai/compiler/utils/IIX.so
startai/compiler/utils/IL.so
startai/compiler/utils/IM.so
startai/compiler/utils/IV.so
startai/compiler/utils/IVI.so
startai/compiler/utils/IX.so
startai/compiler/utils/L.so
startai/compiler/utils/LC.so
startai/compiler/utils/LD.so
startai/compiler/utils/LI.so
startai/compiler/utils/LL.so
startai/compiler/utils/LM.so
startai/compiler/utils/LV.so
startai/compiler/utils/LX.so
startai/compiler/utils/M.so
startai/compiler/utils/MC.so
startai/compiler/utils/MD.so
startai/compiler/utils/MI.so
startai/compiler/utils/ML.so
startai/compiler/utils/MM.so
startai/compiler/utils/MV.so
startai/compiler/utils/MX.so
startai/compiler/utils/V.so
startai/compiler/utils/VC.so
startai/compiler/utils/VD.so
startai/compiler/utils/VI.so
startai/compiler/utils/VL.so
startai/compiler/utils/VM.so
startai/compiler/utils/VV.so
startai/compiler/utils/VX.so
startai/compiler/utils/X.so
startai/compiler/utils/XC.so
startai/compiler/utils/XD.so
startai/compiler/utils/XI.so
startai/compiler/utils/XL.so
startai/compiler/utils/XM.so
startai/compiler/utils/XV.so
startai-0.0.8.0.dist-info/LICENSE
startai-0.0.8.0.dist-info/METADATA
startai-0.0.8.0.dist-info/WHEEL
startai-0.0.8.0.dist-info/top_level.txt
startai-0.0.8.0.dist-info/RECORD
