Metadata-Version: 2.1
Name: startai
Version: 0.0.8.0
Summary: The unified machine learning framework, enabling framework-agnostic functions, layers and libraries.
Home-page: https://khulnasoft.com/startai
Author: Unify
Author-email: hello@khulnasoft.com
License: Apache 2.0
Project-URL: Docs, https://khulnasoft.com/docs/startai/
Project-URL: Source, https://github.com/khulnasoft/startai
Classifier: License :: OSI Approved :: Apache Software License
License-File: LICENSE
Requires-Dist: numpy
Requires-Dist: einops
Requires-Dist: psutil
Requires-Dist: termcolor
Requires-Dist: colorama
Requires-Dist: packaging
Requires-Dist: nvidia-ml-py
Requires-Dist: diskcache
Requires-Dist: google-auth
Requires-Dist: urllib3 <2.0
Requires-Dist: requests
Requires-Dist: pyvis
Requires-Dist: dill
Requires-Dist: astunparse
Requires-Dist: ml-dtypes
Requires-Dist: cloudpickle
Requires-Dist: gast
Requires-Dist: tqdm
Requires-Dist: cryptography
